setup.cfg
setup.py
src/botany_core/__init__.py
src/botany_core/loader.py
src/botany_core/runner.py
src/botany_core/tracer.py
src/botany_core/verifier.py
src/botany_core.egg-info/PKG-INFO
src/botany_core.egg-info/SOURCES.txt
src/botany_core.egg-info/dependency_links.txt
src/botany_core.egg-info/requires.txt
src/botany_core.egg-info/top_level.txt