Metadata-Version: 1.2
Name: botany-core
Version: 0.9.1
Summary: Botany core
Home-page: http://github.com/inglesp/botany
Author: Peter Inglesby
Author-email: peter.inglesby@gmail.com
License: License :: OSI Approved :: MIT License
Platform: UNKNOWN
Requires-Python: >=3.5
